LICENSE
MANIFEST.in
README.rst
qspectrumanalyzer.desktop
qspectrumanalyzer.png
qspectrumanalyzer.svg
setup.py
QSpectrumAnalyzer.egg-info/PKG-INFO
QSpectrumAnalyzer.egg-info/SOURCES.txt
QSpectrumAnalyzer.egg-info/dependency_links.txt
QSpectrumAnalyzer.egg-info/entry_points.txt
QSpectrumAnalyzer.egg-info/requires.txt
QSpectrumAnalyzer.egg-info/top_level.txt
qspectrumanalyzer/__init__.py
qspectrumanalyzer/__main__.py
qspectrumanalyzer/data.py
qspectrumanalyzer/plot.py
qspectrumanalyzer/qspectrumanalyzer.ui
qspectrumanalyzer/qspectrumanalyzer_colors.ui
qspectrumanalyzer/qspectrumanalyzer_persistence.ui
qspectrumanalyzer/qspectrumanalyzer_settings.ui
qspectrumanalyzer/qspectrumanalyzer_settings_help.ui
qspectrumanalyzer/qspectrumanalyzer_smooth.ui
qspectrumanalyzer/ui_qspectrumanalyzer.py
qspectrumanalyzer/ui_qspectrumanalyzer_colors.py
qspectrumanalyzer/ui_qspectrumanalyzer_persistence.py
qspectrumanalyzer/ui_qspectrumanalyzer_settings.py
qspectrumanalyzer/ui_qspectrumanalyzer_settings_help.py
qspectrumanalyzer/ui_qspectrumanalyzer_smooth.py
qspectrumanalyzer/utils.py
qspectrumanalyzer/version.py
qspectrumanalyzer/backends/__init__.py
qspectrumanalyzer/backends/hackrf_sweep.py
qspectrumanalyzer/backends/rtl_power.py
qspectrumanalyzer/backends/rtl_power_fftw.py
qspectrumanalyzer/backends/rx_power.py
qspectrumanalyzer/backends/soapy_power.py
qspectrumanalyzer/languages/qspectrumanalyzer_cs.qm
qspectrumanalyzer/languages/qspectrumanalyzer_cs.ts