Metadata-Version: 1.1
Name: QSpectrumAnalyzer
Version: 1.6.0
Summary: Spectrum analyzer for multiple SDR platforms (PyQtGraph based GUI for soapy_power, rx_power, rtl_power, hackrf_sweep and other backends)
Home-page: https://github.com/xmikos/qspectrumanalyzer
Author: Michal Krenek (Mikos)
Author-email: m.krenek@gmail.com
License: GNU GPLv3
Platform: UNKNOWN
Classifier: Development Status :: 4 - Beta
Classifier: Environment :: MacOS X
Classifier: Environment :: Win32 (MS Windows)
Classifier: Environment :: X11 Applications :: Qt
Classifier: Intended Audience :: End Users/Desktop
Classifier: Intended Audience :: Science/Research
Classifier: Intended Audience :: Telecommunications Industry
Classifier: License :: OSI Approved :: GNU General Public License v3 or later (GPLv3+)
Classifier: Natural Language :: English
Classifier: Operating System :: OS Independent
Classifier: Programming Language :: Python :: 3
Classifier: Topic :: Communications :: Ham Radio
Classifier: Topic :: Scientific/Engineering :: Visualization
